bada/__init__.py
bada/models/__init__.py
bada/models/dsf_input_model.py
bada/models/lightcycler480.py
bada/models/quantstudio7.py
bada/parsers/__init__.py
bada/parsers/base_parser.py
bada/parsers/lightcycler480_parser.py
bada/parsers/quantstudio7_parser.py
bada/processing/__init__.py
bada/processing/feature_extraction.py
bada/processing/preprocessing.py
bada/utils/reformatting.py
bada/utils/utils.py
bada/utils/validation.py
bada/visualization/__init__.py
bada/visualization/heatmap.py
bada/visualization/melting_curves.py
bada-0.1.1.dist-info/METADATA
bada-0.1.1.dist-info/WHEEL
bada-0.1.1.dist-info/licenses/LICENSE
bada-0.1.1.dist-info/RECORD
