Metadata-Version: 2.4
Name: bada
Version: 0.1.1
Summary: Package for analysis of biophysical assays, such as DSF
Author-email: Willi Gottstein <willi.gottstein@gmail.com>
License-File: LICENSE
Requires-Python: >=3.12
Requires-Dist: dtaidistance>=2.3.13
Requires-Dist: numpy>=2.2.3
Requires-Dist: pandas>=2.2.3
Requires-Dist: pandera>=0.23.0
Requires-Dist: plotly>=6.0.0
Requires-Dist: scipy>=1.15.2
